aiger_abc/__init__.py
aiger_abc/simplify.py
py_aiger_abc-0.2.1.dist-info/LICENSE
py_aiger_abc-0.2.1.dist-info/WHEEL
py_aiger_abc-0.2.1.dist-info/METADATA
py_aiger_abc-0.2.1.dist-info/RECORD
