Metadata-Version: 2.1
Name: py-aiger-abc
Version: 0.2.1
Summary: Bridge to using Berkeley-ABC with py-aiger.
Home-page: https://github.com/mvcisback/py-aiger-abc
License: MIT
Author: Marcell Vazquez-Chanlatte
Author-email: mvc@linux.com
Requires-Python: >=3.7,<4.0
Classifier: License :: OSI Approved :: MIT License
Classifier: Programming Language :: Python :: 3
Classifier: Programming Language :: Python :: 3.7
Classifier: Programming Language :: Python :: 3.8
Requires-Dist: py-aiger (>=6.0.0,<7.0.0)
Project-URL: Repository, https://github.com/mvcisback/py-aiger-abc
